{
  "$schema": "https://json-schema.org/draft/2020-12/schema",
  "$id": "#/components/schemas/RegisterCimdClientRequestContent",
  "title": "RegisterCimdClientRequestContent",
  "type": "object",
  "additionalProperties": false,
  "required": [
    "external_client_id"
  ],
  "properties": {
    "external_client_id": {
      "type": "string",
      "description": "URL to the Client ID Metadata Document. Acts as the unique identifier for upsert operations.",
      "minLength": 1,
      "maxLength": 120,
      "format": "absolute-https-uri-or-empty"
    }
  }
}